{
  "updatedAt": "2026-06-23T23:00:57.710Z",
  "banff": {
    "current": {
      "temp": 20,
      "condition": "Overcast",
      "icon": "☁️",
      "humidity": 33,
      "wind": "9 km/h"
    },
    "forecast": [
      {
        "day": "Today",
        "high": 21,
        "low": 3,
        "condition": "Overcast",
        "icon": "☁️"
      },
      {
        "day": "Wednesday",
        "high": 23,
        "low": 8,
        "condition": "Dense drizzle",
        "icon": "🌧️"
      },
      {
        "day": "Thursday",
        "high": 22,
        "low": 9,
        "condition": "Light drizzle",
        "icon": "🌦️"
      },
      {
        "day": "Friday",
        "high": 20,
        "low": 11,
        "condition": "Overcast",
        "icon": "☁️"
      },
      {
        "day": "Saturday",
        "high": 15,
        "low": 9,
        "condition": "Light drizzle",
        "icon": "🌦️"
      }
    ]
  },
  "lakeLouise": {
    "current": {
      "temp": 18,
      "condition": "Clear sky",
      "icon": "☀️",
      "humidity": 37,
      "wind": "8 km/h"
    },
    "forecast": [
      {
        "day": "Today",
        "high": 19,
        "low": 4,
        "condition": "Clear sky",
        "icon": "☀️"
      },
      {
        "day": "Wednesday",
        "high": 20,
        "low": 6,
        "condition": "Partly cloudy",
        "icon": "⛅"
      },
      {
        "day": "Thursday",
        "high": 21,
        "low": 7,
        "condition": "Moderate drizzle",
        "icon": "🌦️"
      },
      {
        "day": "Friday",
        "high": 16,
        "low": 10,
        "condition": "Slight snow showers",
        "icon": "🌨️"
      },
      {
        "day": "Saturday",
        "high": 10,
        "low": 7,
        "condition": "Slight rain",
        "icon": "🌦️"
      }
    ]
  }
}