{
  "updatedAt": "2026-06-07T02:43:12.144Z",
  "banff": {
    "current": {
      "temp": 6,
      "condition": "Mainly clear",
      "icon": "🌤️",
      "humidity": 84,
      "wind": "8 km/h"
    },
    "forecast": [
      {
        "day": "Today",
        "high": 13,
        "low": 2,
        "condition": "Slight snowfall",
        "icon": "🌨️"
      },
      {
        "day": "Sunday",
        "high": 9,
        "low": 2,
        "condition": "Slight snowfall",
        "icon": "🌨️"
      },
      {
        "day": "Monday",
        "high": 14,
        "low": 2,
        "condition": "Overcast",
        "icon": "☁️"
      },
      {
        "day": "Tuesday",
        "high": 8,
        "low": 5,
        "condition": "Moderate snowfall",
        "icon": "🌨️"
      },
      {
        "day": "Wednesday",
        "high": 10,
        "low": 5,
        "condition": "Moderate snowfall",
        "icon": "🌨️"
      }
    ]
  },
  "lakeLouise": {
    "current": {
      "temp": 4,
      "condition": "Partly cloudy",
      "icon": "⛅",
      "humidity": 87,
      "wind": "9 km/h"
    },
    "forecast": [
      {
        "day": "Today",
        "high": 8,
        "low": 2,
        "condition": "Moderate snowfall",
        "icon": "🌨️"
      },
      {
        "day": "Sunday",
        "high": 6,
        "low": 1,
        "condition": "Overcast",
        "icon": "☁️"
      },
      {
        "day": "Monday",
        "high": 10,
        "low": 2,
        "condition": "Overcast",
        "icon": "☁️"
      },
      {
        "day": "Tuesday",
        "high": 7,
        "low": 0,
        "condition": "Slight snow showers",
        "icon": "🌨️"
      },
      {
        "day": "Wednesday",
        "high": 9,
        "low": 4,
        "condition": "Moderate snowfall",
        "icon": "🌨️"
      }
    ]
  }
}