{
  "updatedAt": "2026-07-03T22:55:47.089Z",
  "banff": {
    "current": {
      "temp": 19,
      "condition": "Clear sky",
      "icon": "☀️",
      "humidity": 33,
      "wind": "23 km/h"
    },
    "forecast": [
      {
        "day": "Today",
        "high": 20,
        "low": 8,
        "condition": "Light drizzle",
        "icon": "🌦️"
      },
      {
        "day": "Saturday",
        "high": 21,
        "low": 11,
        "condition": "Overcast",
        "icon": "☁️"
      },
      {
        "day": "Sunday",
        "high": 21,
        "low": 7,
        "condition": "Moderate drizzle",
        "icon": "🌦️"
      },
      {
        "day": "Monday",
        "high": 24,
        "low": 7,
        "condition": "Overcast",
        "icon": "☁️"
      },
      {
        "day": "Tuesday",
        "high": 26,
        "low": 12,
        "condition": "Overcast",
        "icon": "☁️"
      }
    ]
  },
  "lakeLouise": {
    "current": {
      "temp": 15,
      "condition": "Mainly clear",
      "icon": "🌤️",
      "humidity": 63,
      "wind": "16 km/h"
    },
    "forecast": [
      {
        "day": "Today",
        "high": 16,
        "low": 9,
        "condition": "Light drizzle",
        "icon": "🌦️"
      },
      {
        "day": "Saturday",
        "high": 16,
        "low": 8,
        "condition": "Overcast",
        "icon": "☁️"
      },
      {
        "day": "Sunday",
        "high": 17,
        "low": 3,
        "condition": "Light drizzle",
        "icon": "🌦️"
      },
      {
        "day": "Monday",
        "high": 21,
        "low": 6,
        "condition": "Overcast",
        "icon": "☁️"
      },
      {
        "day": "Tuesday",
        "high": 24,
        "low": 11,
        "condition": "Clear sky",
        "icon": "☀️"
      }
    ]
  }
}